wagtailembedpeertube/__init__.py
wagtailembedpeertube/apps.py
wagtailembedpeertube/finders.py
wagtailembedpeertube-0.2.0.dist-info/LICENSE
wagtailembedpeertube-0.2.0.dist-info/METADATA
wagtailembedpeertube-0.2.0.dist-info/WHEEL
wagtailembedpeertube-0.2.0.dist-info/top_level.txt
wagtailembedpeertube-0.2.0.dist-info/RECORD
