Metadata-Version: 2.1
Name: wagtailembedpeertube
Version: 0.2.0
Summary: Embed PeerTube videos into Wagtail
Home-page: https://forge.cliss21.org/cliss21/wagtailembedpeertube
Author: Cliss XXI
Author-email: contact@cliss21.com
License: GNU AGPL-3
Project-URL: Bug Tracker, https://forge.cliss21.org/cliss21/wagtailembedpeertube/issues
Project-URL: Source Code, https://forge.cliss21.org/cliss21/wagtailembedpeertube
Platform: UNKNOWN
Classifier: Environment :: Web Environment
Classifier: Framework :: Django
Classifier: Framework :: Wagtail
Classifier: Framework :: Wagtail :: 2
Classifier: Intended Audience :: Developers
Classifier: License :: OSI Approved :: GNU Affero General Public License v3 or later (AGPLv3+)
Classifier: Operating System :: OS Independent
Classifier: Programming Language :: Python :: 3
Classifier: Programming Language :: Python :: 3.7
Classifier: Programming Language :: Python :: 3.8
Classifier: Programming Language :: Python :: 3.9
Classifier: Topic :: Internet :: WWW/HTTP
Classifier: Topic :: Internet :: WWW/HTTP :: Dynamic Content
Requires-Dist: wagtail (>=2.0)
Provides-Extra: test
Requires-Dist: black ; extra == 'test'
Requires-Dist: coverage ; extra == 'test'
Requires-Dist: flake8-black ; extra == 'test'
Requires-Dist: flake8-isort ; extra == 'test'
Requires-Dist: flake8 (>=3.5) ; extra == 'test'
Requires-Dist: isort (>=5.0) ; extra == 'test'
